approval_validator/__init__.py
approval_validator/change_set.py
approval_validator/changed_directory.py
approval_validator/cli.py
approval_validator/cli_utils.py
approval_validator/exceptions.py
approval_validator/file_utils.py
approval_validator/tests/__init__.py
approval_validator/tests/changed_directory_test.py
approval_validator/tests/file_utils_test.py
approvals_validator-0.2.1.data/scripts/validate_approvals
approvals_validator-0.2.1.dist-info/LICENSE
approvals_validator-0.2.1.dist-info/METADATA
approvals_validator-0.2.1.dist-info/WHEEL
approvals_validator-0.2.1.dist-info/top_level.txt
approvals_validator-0.2.1.dist-info/RECORD
