Metadata-Version: 2.1
Name: approvals-validator
Version: 0.2.1
Summary: A CLI tool to validate changeset approvals.
Home-page: https://github.com/jmromer/approvals_validator
Author: Jake Romer
Author-email: mail@jakeromer.com
License: UNKNOWN
Platform: UNKNOWN
Classifier: Programming Language :: Python :: 3.8
Classifier: License :: OSI Approved :: MIT License
Classifier: Operating System :: OS Independent
Requires-Python: >=3.8
Requires-Dist: click
Requires-Dist: colorama
